cmake_init_lib/__init__.py
cmake_init_lib/__main__.py
cmake_init_lib/cmake_init.py
cmake_init_lib/template.py
cmake_init_lib/templates/LICENSE
cmake_init_lib/templates/README.md
cmake_init_lib/templates/c/common/.clang-tidy
cmake_init_lib/templates/c/common/example/CMakeLists.txt
cmake_init_lib/templates/c/common/example/empty_example.c
cmake_init_lib/templates/c/executable/CMakeLists.txt
cmake_init_lib/templates/c/executable/source/lib.c
cmake_init_lib/templates/c/executable/source/lib.h
cmake_init_lib/templates/c/executable/source/main.c
cmake_init_lib/templates/c/executable/test/source/__name___test.c
cmake_init_lib/templates/c/header/CMakeLists.txt
cmake_init_lib/templates/c/header/include/__name__/__name__.h
cmake_init_lib/templates/c/header/test/source/__name___test.c
cmake_init_lib/templates/c/header/test/source/header_impl.c
cmake_init_lib/templates/c/shared/CMakeLists.txt
cmake_init_lib/templates/c/shared/include/__name__/__name__.h
cmake_init_lib/templates/c/shared/source/__name__.c
cmake_init_lib/templates/c/shared/test/source/__name___test.c
cmake_init_lib/templates/common/.clang-format
cmake_init_lib/templates/common/.clang-tidy
cmake_init_lib/templates/common/.clangd
cmake_init_lib/templates/common/.codespellrc
cmake_init_lib/templates/common/.gitignore
cmake_init_lib/templates/common/BUILDING.md
cmake_init_lib/templates/common/CMakePresets.json
cmake_init_lib/templates/common/CMakeUserPresets.json
cmake_init_lib/templates/common/CODE_OF_CONDUCT.md
cmake_init_lib/templates/common/CONTRIBUTING.md
cmake_init_lib/templates/common/HACKING.md
cmake_init_lib/templates/common/README.md
cmake_init_lib/templates/common/conan-setup.sh
cmake_init_lib/templates/common/conanfile.py
cmake_init_lib/templates/common/env.bat
cmake_init_lib/templates/common/env.ps1
cmake_init_lib/templates/common/vcpkg.json
cmake_init_lib/templates/common/.github/scripts/conan-ci-setup.sh
cmake_init_lib/templates/common/.github/workflows/ci.yml
cmake_start-1.0.16.dist-info/METADATA
cmake_start-1.0.16.dist-info/WHEEL
cmake_start-1.0.16.dist-info/entry_points.txt
cmake_start-1.0.16.dist-info/licenses/COPYING
cmake_start-1.0.16.dist-info/RECORD
