Metadata-Version: 2.4
Name: cmake-start
Version: 1.0.16
Summary: The missing CMake project initializer
Project-URL: Homepage, https://github.com/friendlyanon/cmake-init
Project-URL: Repository, https://github.com/friendlyanon/cmake-init
Project-URL: Issues, https://github.com/friendlyanon/cmake-init/issues
Author-email: friendlyanon <friendlyanon_@hotmail.com>
License: GPL-3.0-or-later
License-File: COPYING
Keywords: build-tools,cmake,project-initializer,utilities
Classifier: Development Status :: 4 - Beta
Classifier: Environment :: Console
Classifier: Intended Audience :: Developers
Classifier: License :: OSI Approved :: GNU General Public License v3 (GPLv3)
Classifier: Operating System :: OS Independent
Classifier: Programming Language :: C
Classifier: Programming Language :: C++
Classifier: Programming Language :: Python :: 3
Classifier: Programming Language :: Python :: 3.8
Classifier: Programming Language :: Python :: 3.9
Classifier: Programming Language :: Python :: 3.10
Classifier: Programming Language :: Python :: 3.11
Classifier: Programming Language :: Python :: 3.12
Classifier: Programming Language :: Python :: 3.13
Classifier: Topic :: Software Development :: Build Tools
Classifier: Topic :: Utilities
Requires-Python: >=3.8
